omterms/__init__.py
omterms/__version__.py
omterms/cleaner.py
omterms/datauis.py
omterms/interface.py
omterms/measures.py
omterms/stemmer.py
omterms/tokenizer.py
omterms/utilities.py
omterms-0.1.4.dist-info/DESCRIPTION.rst
omterms-0.1.4.dist-info/METADATA
omterms-0.1.4.dist-info/RECORD
omterms-0.1.4.dist-info/WHEEL
omterms-0.1.4.dist-info/entry_points.txt
omterms-0.1.4.dist-info/metadata.json
omterms-0.1.4.dist-info/top_level.txt
