Metadata-Version: 2.0
Name: omterms
Version: 0.1.4
Summary: A customizable keyword extraction package.
Home-page: http://github.com/bulentozel/omterms
Author: Bulent Ozel
Author-email: bulent.ozel@gmail.com
License: Apache2
Platform: UNKNOWN
Classifier: License :: OSI Approved :: Apache Software License
Classifier: Development Status :: 2 - Pre-Alpha
Classifier: Programming Language :: Python
Classifier: Programming Language :: Python :: 3.6
Classifier: Intended Audience :: Developers
Classifier: Intended Audience :: Science/Research
Classifier: Topic :: Text Processing :: General
Classifier: Topic :: Scientific/Engineering :: Information Analysis
Requires-Python: >=3.6.0
Requires-Dist: matplotlib
Requires-Dist: nltk
Requires-Dist: numpy
Requires-Dist: pandas
Requires-Dist: scikit-learn
Requires-Dist: scipy
